README.txt
setup.cfg
setup.py
hanzi2pinyin/__init__.py
hanzi2pinyin/h2p.py
hanzi2pinyin/quickh2p.py
hanzi2pinyin.egg-info/PKG-INFO
hanzi2pinyin.egg-info/SOURCES.txt
hanzi2pinyin.egg-info/dependency_links.txt
hanzi2pinyin.egg-info/entry_points.txt
hanzi2pinyin.egg-info/not-zip-safe
hanzi2pinyin.egg-info/top_level.txt