Metadata-Version: 1.0
Name: hanzi2pinyin
Version: 0.1
Summary: 汉字转拼音
Home-page: http://www.flyzen.com
Author: Young King
Author-email: youngking@flyzen.com
License: BSD
Keywords: chinese hanzi translate pinyin
Platform: UNKNOWN
Classifier: Programming Language :: Python
Classifier: License :: OSI Approved :: BSD License
